libenergyplusapi.so
libenergyplusapi.so.25.1.0
pyenergyplus/__init__.py
pyenergyplus/api.py
pyenergyplus/common.py
pyenergyplus/dataset.py
pyenergyplus/datatransfer.py
pyenergyplus/func.py
pyenergyplus/plugin.py
pyenergyplus/runtime.py
pyenergyplus/state.py
pyenergyplus/data/model/ASHRAE901_ApartmentHighRise_STD2019_Denver.idf
pyenergyplus/data/model/ASHRAE901_ApartmentMidRise_STD2019_Denver.idf
pyenergyplus/data/model/ASHRAE901_Hospital_STD2019_Denver.idf
pyenergyplus/data/model/ASHRAE901_HotelLarge_STD2019_Denver.idf
pyenergyplus/data/model/ASHRAE901_HotelSmall_STD2019_Denver.idf
pyenergyplus/data/model/ASHRAE901_OfficeLarge_STD2019_Denver.idf
pyenergyplus/data/model/ASHRAE901_OfficeMedium_STD2019_Denver.idf
pyenergyplus/data/model/ASHRAE901_OfficeSmall_STD2019_Denver.idf
pyenergyplus/data/model/ASHRAE901_OutPatientHealthCare_STD2019_Denver.idf
pyenergyplus/data/model/ASHRAE901_RestaurantFastFood_STD2019_Denver.idf
pyenergyplus/data/model/ASHRAE901_RestaurantSitDown_STD2019_Denver.idf
pyenergyplus/data/model/ASHRAE901_RetailStandalone_STD2019_Denver.idf
pyenergyplus/data/model/ASHRAE901_RetailStripmall_STD2019_Denver.idf
pyenergyplus/data/model/ASHRAE901_SchoolPrimary_STD2019_Denver.idf
pyenergyplus/data/model/ASHRAE901_SchoolSecondary_STD2019_Denver.idf
pyenergyplus/data/model/ASHRAE901_Warehouse_STD2019_Denver.idf
pyenergyplus/data/model/RefBldgFullServiceRestaurantNew2004_Chicago.idf
pyenergyplus/data/model/RefBldgHospitalNew2004_Chicago.idf
pyenergyplus/data/model/RefBldgLargeHotelNew2004_Chicago.idf
pyenergyplus/data/model/RefBldgLargeOfficeNew2004_Chicago.idf
pyenergyplus/data/model/RefBldgMediumOfficeNew2004_Chicago.idf
pyenergyplus/data/model/RefBldgMidriseApartmentNew2004_Chicago.idf
pyenergyplus/data/model/RefBldgOutPatientNew2004_Chicago.idf
pyenergyplus/data/model/RefBldgPrimarySchoolNew2004_Chicago.idf
pyenergyplus/data/model/RefBldgQuickServiceRestaurantNew2004_Chicago.idf
pyenergyplus/data/model/RefBldgSecondarySchoolNew2004_Chicago.idf
pyenergyplus_lbnl-25.1.2.dist-info/LICENSE.txt
pyenergyplus_lbnl-25.1.2.dist-info/METADATA
pyenergyplus_lbnl-25.1.2.dist-info/WHEEL
pyenergyplus_lbnl-25.1.2.dist-info/top_level.txt
pyenergyplus_lbnl-25.1.2.dist-info/RECORD
