Metadata-Version: 2.1
Name: pyenergyplus-lbnl
Version: 25.1.2
Summary: Direct port of pyenergyplus that comes with EnergyPlus into a standalone Python package
Home-page: https://github.com/taoning/pyenergyplus
Author: LBNL
Author-email: taoningwang@lbl.gov
License: LICENSE.txt
Platform: UNKNOWN
License-File: LICENSE.txt
